groestlcoin_hash.cp310-win32.pyd
groestlcoin_hash-1.0.3.dist-info/METADATA
groestlcoin_hash-1.0.3.dist-info/WHEEL
groestlcoin_hash-1.0.3.dist-info/top_level.txt
groestlcoin_hash-1.0.3.dist-info/RECORD
