Metadata-Version: 2.1
Name: groestlcoin-hash
Version: 1.0.3
Summary: Groestlcoin hash algorithm.
Home-page: https://github.com/Groestlcoin/groestlcoin-hash-python
Maintainer: Groestlcoin Developers
Maintainer-email: groestlcoin@gmail.com
License: UNKNOWN
Keywords: groestlcoin,grs
Platform: UNKNOWN
